ilv/__init__.py
ilv/utils.py
ilv/vis_log.py
ilv/collect_results/__init__.py
ilv/collect_results/collect_results_chainer.py
ilv/collect_results/interactive.py
ilv/train/__init__.py
ilv/train/train_helper.py
ilv-0.1.dist-info/DESCRIPTION.rst
ilv-0.1.dist-info/METADATA
ilv-0.1.dist-info/RECORD
ilv-0.1.dist-info/WHEEL
ilv-0.1.dist-info/metadata.json
ilv-0.1.dist-info/top_level.txt
