Metadata-Version: 2.0
Name: ilv
Version: 0.1
Summary: Interactive log visualizer for neural networks using Bokeh
Home-page: http://github.com/yuyu2172/ilv
Author: Yusuke Niitani
Author-email: yuyuniitani@gmail.com
License: MIT
Platform: UNKNOWN
Requires-Dist: bokeh (>=0.12.4)
Requires-Dist: numpy (>=1.11)
Requires-Dist: pandas
